{
  "variants": {
    "facing=south": {
      "model": "sonicraft:block/studiopolis_pillar"
    },
    "facing=north": {
      "model": "sonicraft:block/studiopolis_pillar"
    },
    "facing=east": {
      "model": "sonicraft:block/studiopolis_pillar",
      "x": 90
    },
    "facing=west": {
      "model": "sonicraft:block/studiopolis_pillar",
      "x": 90
    },
    "facing=up": {
      "model": "sonicraft:block/studiopolis_pillar",
      "x": 90,
      "y": 90
    },
    "facing=down": {
      "model": "sonicraft:block/studiopolis_pillar",
      "x": 90,
      "y": 90
    }
  }
}